pdfmang/__init__.py
pdfmang/main.py
pdfmang/modules/__init__.py
pdfmang/modules/compress_tool.py
pdfmang/modules/convert_tool.py
pdfmang/modules/encrypt_tool.py
pdfmang/modules/merge_tool.py
pdfmang/modules/split_tool.py
pdfmang-1.0.0.dist-info/licenses/LICENSE
pdfmang-1.0.0.dist-info/METADATA
pdfmang-1.0.0.dist-info/WHEEL
pdfmang-1.0.0.dist-info/entry_points.txt
pdfmang-1.0.0.dist-info/top_level.txt
pdfmang-1.0.0.dist-info/RECORD
