Metadata-Version: 2.4
Name: pdfmang
Version: 1.0.0
Summary: A free and open-source PDF Utility Suite built with Tkinter
Home-page: https://github.com/yatinannam/pdfmang
Author: Yatin Annam
Author-email: Yatin Annam <ninjayatin@gmail.com>
License: MIT
Requires-Python: >=3.8
License-File: LICENSE
Requires-Dist: PyPDF2
Requires-Dist: ttkthemes
Requires-Dist: pdf2image
Requires-Dist: pdf2docx
Requires-Dist: pillow
Dynamic: author
Dynamic: home-page
Dynamic: license-file
Dynamic: requires-python
